bigpi/__init__.py
bigpi/sean_func.py
bigpi/sean_func1.py
bigpi-0.0.2.dist-info/METADATA
bigpi-0.0.2.dist-info/WHEEL
bigpi-0.0.2.dist-info/top_level.txt
bigpi-0.0.2.dist-info/RECORD
