Metadata-Version: 2.1
Name: bigpi
Version: 0.0.2
Summary: this is my test package
Home-page: https://github.com/twmllsh
Author: Sean Lee
Author-email: twmllsh@gmail.com
Classifier: Programming Language :: Python :: 3
Classifier: License :: OSI Approved :: MIT License
Classifier: Operating System :: OS Independent
Requires-Python: >=3.7
